PyngPong/__init__.py
PyngPong-1.0.dist-info/LICENSE.txt
PyngPong-1.0.dist-info/METADATA
PyngPong-1.0.dist-info/WHEEL
PyngPong-1.0.dist-info/top_level.txt
PyngPong-1.0.dist-info/RECORD
