Metadata-Version: 2.1
Name: PyngPong
Version: 1.0
Summary: PyngPong is a pre-built pong game
Home-page: https://github.com/Ankit404butfound/PyngPong
Author: Ankit Raj Mahapatra
Author-email: ankitrajjitendra816@gmail.com
License: MIT
Download-URL: https://github.com/Ankit404butfound/awesomepy/archive/1.0.tar.gz
Keywords: play()
Platform: UNKNOWN
Classifier: Development Status :: 3 - Alpha
Classifier: Intended Audience :: Developers
Classifier: Topic :: Software Development :: Build Tools
Classifier: License :: OSI Approved :: MIT License
Classifier: Programming Language :: Python :: 3
Classifier: Programming Language :: Python :: 3.4
Classifier: Programming Language :: Python :: 3.5
Classifier: Programming Language :: Python :: 3.6
Requires-Dist: keyboard
